{
  "id": "setup/ros2-environment-setup",
  "title": "ROS 2 Environment Sourcing Guide with bashrc Modifications",
  "description": "Overview",
  "source": "@site/docs/setup/ros2-environment-setup.md",
  "sourceDirName": "setup",
  "slug": "/setup/ros2-environment-setup",
  "permalink": "/docs/setup/ros2-environment-setup",
  "draft": false,
  "unlisted": false,
  "editUrl": "https://github.com/facebook/docusaurus/tree/main/packages/create-docusaurus/templates/shared/docs/setup/ros2-environment-setup.md",
  "tags": [],
  "version": "current",
  "frontMatter": {},
  "sidebar": "tutorialSidebar",
  "previous": {
    "title": "ROS 2 Humble Hawksbill Installation and Setup",
    "permalink": "/docs/setup/ros2-setup"
  },
  "next": {
    "title": "ROS 2 Workspace Structure",
    "permalink": "/docs/setup/ros2-workspace-structure"
  }
}